pyexcreporter/__init__.py
pyexcreporter/abstract_backend.py
pyexcreporter/main.py
pyexcreporter/singleton_meta.py
pyexcreporter/backends/__init__.py
pyexcreporter/backends/smtp_backend.py
pyexcreporter-0.1.dist-info/LICENSE
pyexcreporter-0.1.dist-info/METADATA
pyexcreporter-0.1.dist-info/WHEEL
pyexcreporter-0.1.dist-info/top_level.txt
pyexcreporter-0.1.dist-info/RECORD
