Metadata-Version: 2.1
Name: pyexcreporter
Version: 0.1
Summary: An exception reporter utility.
Home-page: https://github.com/zaki-x86/pyexcreporter.git
Author: Mohamed Zaki
Author-email: zaki.x86@gmail.com
License: MIT License
Classifier: Programming Language :: Python :: 3
License-File: LICENSE
